{
  "courses": [
    {
      "id": "gun1c1",
      "code": "GUN 1C1",
      "name": "English I",
      "prerequisites": [],
      "creditHours": 2
    },
    {
      "id": "gun2c1",
      "code": "GUN 2C1",
      "name": "English II",
      "prerequisites": ["gun1c1"],
      "creditHours": 2
    },
    {
      "id": "gunuc1",
      "code": "GUN UC1",
      "name": "University Requirement (Compulsory)",
      "prerequisites": [],
      "creditHours": 2
    },
    {
      "id": "gunuc2",
      "code": "GUN UC2",
      "name": "University Requirement (Compulsory) II",
      "prerequisites": [],
      "creditHours": 2
    },
    {
      "id": "gunue1",
      "code": "GUN UE1",
      "name": "University Requirement (Elective) I",
      "prerequisites": [],
      "creditHours": 2
    },
    {
      "id": "gunue2",
      "code": "GUN UE2",
      "name": "University Requirement (Elective) II",
      "prerequisites": [],
      "creditHours": 2
    },
    {
      "id": "gap112",
      "code": "GAP 112",
      "name": "Statistics & Probability",
      "prerequisites": ["gap114"],
      "creditHours": 3
    },
    {
      "id": "gap114",
      "code": "GAP 114",
      "name": "Mathematics",
      "prerequisites": [],
      "creditHours": 3
    },
    {
      "id": "gap121",
      "code": "GAP 121",
      "name": "Physics",
      "prerequisites": [],
      "creditHours": 3
    },
    {
      "id": "ect113",
      "code": "ECT 113",
      "name": "Information Technology",
      "prerequisites": [],
      "creditHours": 3
    },
    {
      "id": "ect121",
      "code": "ECT 121",
      "name": "Computer Programming",
      "prerequisites": ["gap114"],
      "creditHours": 3
    },
    {
      "id": "ect122",
      "code": "ECT 122",
      "name": "Operating Systems",
      "prerequisites": ["ect121"],
      "creditHours": 2
    },
    {
      "id": "ect231",
      "code": "ECT 231",
      "name": "Internet of Things (IOT)",
      "prerequisites": ["ect142"],
      "creditHours": 3
    },
    {
      "id": "ect141",
      "code": "ECT 141",
      "name": "Data Communication",
      "prerequisites": ["gap121"],
      "creditHours": 3
    },
    {
      "id": "ect142",
      "code": "ECT 142",
      "name": "Computer Network",
      "prerequisites": ["ect141"],
      "creditHours": 3
    },
    {
      "id": "ect241",
      "code": "ECT 241",
      "name": "Network Security",
      "prerequisites": ["ect141"],
      "creditHours": 3
    },
    {
      "id": "ect242",
      "code": "ECT 242",
      "name": "Computer Networks II",
      "prerequisites": ["ect142"],
      "creditHours": 3
    },
    {
      "id": "ect243",
      "code": "ECT 243",
      "name": "LAN Design",
      "prerequisites": ["ect141"],
      "creditHours": 3
    },
    {
      "id": "ect274",
      "code": "ECT 274",
      "name": "Logic Design",
      "prerequisites": ["ect121"],
      "creditHours": 3
    },
    {
      "id": "ect372",
      "code": "ECT 372",
      "name": "Computer Design & Architecture",
      "prerequisites": ["ect274"],
      "creditHours": 3
    },
    {
      "id": "ect373",
      "code": "ECT 373",
      "name": "Computer Maintenance",
      "prerequisites": ["ect372"],
      "creditHours": 3
    },
    {
      "id": "ect191",
      "code": "ECT 191",
      "name": "Field Training I (Summer Year I)",
      "prerequisites": [],
      "creditHours": 3
    },
    {
      "id": "ect291",
      "code": "ECT 291",
      "name": "Diploma IT Project",
      "prerequisites": ["completion_first_year"],
      "creditHours": 3
    },
    {
      "id": "ect292",
      "code": "ECT 292",
      "name": "Diploma IT Project II",
      "prerequisites": ["ect291"],
      "creditHours": 4
    },
    {
      "id": "ect293",
      "code": "ECT 293",
      "name": "Field Training II (Summer Year 2)",
      "prerequisites": [],
      "creditHours": 3
    }
  ]
}